cloney/__init__.py
cloney/check_buckets.py
cloney/logger.py
cloney/main.py
cloney/storage.py
cloney/utils.py
cloney/verify.py
cloney-1.1.2.dist-info/licenses/LICENSE
cloney-1.1.2.dist-info/METADATA
cloney-1.1.2.dist-info/WHEEL
cloney-1.1.2.dist-info/entry_points.txt
cloney-1.1.2.dist-info/top_level.txt
cloney-1.1.2.dist-info/RECORD
