Metadata-Version: 2.4
Name: cloney
Version: 1.1.2
Summary: A CLI tool for migrating files between cloud storage services
Requires-Python: >=3.7
License-File: LICENSE
Requires-Dist: boto3
Requires-Dist: google-cloud-storage
Requires-Dist: oss2
Requires-Dist: azure-storage-blob
Dynamic: license-file
